README.txt
setup.cfg
setup.py
docs/HISTORY.txt
docs/INSTALL.txt
docs/LICENSE.GPL
docs/LICENSE.txt
easyshop/__init__.py
easyshop.core.egg-info/PKG-INFO
easyshop.core.egg-info/SOURCES.txt
easyshop.core.egg-info/dependency_links.txt
easyshop.core.egg-info/entry_points.txt
easyshop.core.egg-info/namespace_packages.txt
easyshop.core.egg-info/not-zip-safe
easyshop.core.egg-info/requires.txt
easyshop.core.egg-info/top_level.txt
easyshop/core/__init__.py
easyshop/core/catalog.py
easyshop/core/config.py
easyshop/core/configure.zcml
easyshop/core/permissions.zcml
easyshop/core/profile.py
easyshop/core/profiles.zcml
easyshop/core/version.txt
easyshop/core/vocabularies.py
easyshop/core/Extensions/Install.py
easyshop/core/Extensions/__init__.py
easyshop/core/browser/__init__.py
easyshop/core/browser/configure.zcml
easyshop/core/browser/default_shop_form.pt
easyshop/core/browser/global.py
easyshop/core/interfaces/__init__.py
easyshop/core/interfaces/carts.py
easyshop/core/interfaces/catalog.py
easyshop/core/interfaces/checkout.py
easyshop/core/interfaces/copy.py
easyshop/core/interfaces/criteria.py
easyshop/core/interfaces/currency.py
easyshop/core/interfaces/customers.py
easyshop/core/interfaces/data.py
easyshop/core/interfaces/discounts.py
easyshop/core/interfaces/groups.py
easyshop/core/interfaces/information.py
easyshop/core/interfaces/item.py
easyshop/core/interfaces/misc.py
easyshop/core/interfaces/orders.py
easyshop/core/interfaces/payment.py
easyshop/core/interfaces/price.py
easyshop/core/interfaces/search.py
easyshop/core/interfaces/sessions.py
easyshop/core/interfaces/shipping.py
easyshop/core/interfaces/shop.py
easyshop/core/interfaces/stocks.py
easyshop/core/interfaces/taxes.py
easyshop/core/interfaces/utilities.py
easyshop/core/profiles/__init__.py
easyshop/core/tests/__init__.py
easyshop/core/tests/base.py
easyshop/core/tests/readme.txt
easyshop/core/tests/template.py
easyshop/core/tests/test.jpg
easyshop/core/tests/test_2.jpg
easyshop/core/tests/test_adapter_cart.py
easyshop/core/tests/test_adapter_cartitem.py
easyshop/core/tests/test_adapter_category.py
easyshop/core/tests/test_adapter_criteria.py
easyshop/core/tests/test_adapter_customer_address.py
easyshop/core/tests/test_adapter_customer_completeness.py
easyshop/core/tests/test_adapter_customer_payment.py
