Metadata-Version: 1.0
Name: easyshop.core
Version: 0.1a1
Summary: An out-of-the-box online shop for Plone.
Home-page: http://iqpp.de
Author: Kai Diefenbach
Author-email: kai.diefenbach@iqpp.de
License: GPL
Platform: UNKNOWN
Classifier: Framework :: Plone
Classifier: Framework :: Zope2
Classifier: Framework :: Zope3
Classifier: Programming Language :: Python
Classifier: Topic :: Software Development :: Libraries :: Python Modules
